datasource/__init__.py
datasource/mastodon/__init__.py
datasource/mastodon/download_conversations_mastodon.py
datasource/mastodon/download_daily_political_sample_mstd.py
datasource/mastodon/download_user_conversations.py
datasource/reddit/__init__.py
datasource/reddit/download_conversations_reddit.py
datasource/reddit/download_daily_political_rd_sample.py
datasource/reddit/download_user_conversations.py
datasource/twitter/__init__.py
datasource/twitter/download_conversations_twitter.py
datasource/twitter/download_daily_political_sample.py
tests/__init__.py
tests/mastodon_tests.py
tests/reddit_tests.py
tests/run_tests.py
tests/twitter_tests.py
delab_socialmedia-0.3.6.dist-info/LICENSE
delab_socialmedia-0.3.6.dist-info/METADATA
delab_socialmedia-0.3.6.dist-info/WHEEL
delab_socialmedia-0.3.6.dist-info/top_level.txt
delab_socialmedia-0.3.6.dist-info/RECORD
