Metadata-Version: 2.1
Name: delab-socialmedia
Version: 0.3.6
Summary: a library to download reply trees in forums and social media
Home-page: https://github.com/juliandehne/delab-socialmedia
Author: Julian Dehne
Author-email: julian.dehne@gmail.com
License: MIT
Classifier: Intended Audience :: Developers
Classifier: License :: OSI Approved :: MIT License
Classifier: Programming Language :: Python :: 3.9
Classifier: Operating System :: OS Independent
License-File: LICENSE
Requires-Dist: delab-trees
Requires-Dist: Mastodon.py
Requires-Dist: twarc ==2.8.0
Requires-Dist: PyYAML
Requires-Dist: pytest ==7.1.2
Requires-Dist: attrs
Requires-Dist: python-dotenv
